consulservicefinder/__init__.py
consulservicefinder/consulservicefinder.py
consulservicefinder-0.0.4.dist-info/METADATA
consulservicefinder-0.0.4.dist-info/RECORD
consulservicefinder-0.0.4.dist-info/WHEEL
consulservicefinder-0.0.4.dist-info/top_level.txt
