Metadata-Version: 2.1
Name: consulservicefinder
Version: 0.0.4
Summary: Find service from Consul
Home-page: https://github.com/PrinsWu/consulservicefinder
Author: Prins Wu
Author-email: prinswu@gmail.com
License: UNKNOWN
Keywords: consul microservice
Platform: UNKNOWN
Classifier: Development Status :: 3 - Alpha
Classifier: Intended Audience :: Developers
Classifier: Programming Language :: Python :: 3
Classifier: License :: OSI Approved :: MIT License
Classifier: Operating System :: OS Independent
Requires-Python: >=3
Requires-Dist: requests (==2.19.1)
Requires-Dist: python-consul (==1.1.0)
